{
  "kind": "collectionType",
  "collectionName": "trails",
  "info": {
    "singularName": "trail",
    "pluralName": "trails",
    "displayName": "Trail",
    "description": ""
  },
  "options": {
    "draftAndPublish": false
  },
  "pluginOptions": {},
  "attributes": {
    "city": {
      "type": "relation",
      "relation": "oneToOne",
      "target": "api::city.city"
    },
    "country": {
      "type": "relation",
      "relation": "oneToOne",
      "target": "api::country.country"
    },
    "state": {
      "type": "relation",
      "relation": "oneToOne",
      "target": "api::state.state"
    },
    "slug": {
      "type": "uid"
    },
    "name": {
      "type": "string",
      "required": true
    },
    "website": {
      "type": "string"
    },
    "category": {
      "type": "string"
    },
    "address": {
      "type": "string"
    },
    "zip": {
      "type": "string"
    },
    "googleReviewAvg": {
      "type": "decimal"
    },
    "googleReviewCount": {
      "type": "integer"
    },
    "googleMapsLink": {
      "type": "string"
    }
  }
}
